reflink/__init__.py
reflink/_backend.pyd
reflink/backend.py
reflink/darwin.c
reflink/error.py
reflink/linux.c
reflink/native.py
reflink/reflink.py
reflink/win32.c
reflink-0.2.2.dist-info/AUTHORS.rst
reflink-0.2.2.dist-info/LICENSE
reflink-0.2.2.dist-info/METADATA
reflink-0.2.2.dist-info/WHEEL
reflink-0.2.2.dist-info/top_level.txt
reflink-0.2.2.dist-info/RECORD
