Metadata-Version: 2.1
Name: reflink
Version: 0.2.2
Summary: Python reflink wraps around platform specific reflink implementations
Home-page: https://gitlab.com/rubdos/pyreflink
Author: Ruben De Smet
Author-email: pypi@rubdos.be
License: MIT license
Keywords: reflink
Classifier: Development Status :: 2 - Pre-Alpha
Classifier: Intended Audience :: Developers
Classifier: License :: OSI Approved :: MIT License
Classifier: Natural Language :: English
Classifier: Programming Language :: Python :: 2
Classifier: Programming Language :: Python :: 2.6
Classifier: Programming Language :: Python :: 2.7
Classifier: Programming Language :: Python :: 3
Classifier: Programming Language :: Python :: 3.4
Classifier: Programming Language :: Python :: 3.5
Classifier: Programming Language :: Python :: 3.6
Classifier: Programming Language :: Python :: 3.7
License-File: LICENSE
License-File: AUTHORS.rst
